jackbox/__init__.py
jackbox/_http.py
jackbox/_wss.py
jackbox/bombintern.py
jackbox/client.py
jackbox/enums/__init__.py
jackbox/enums/bombintern.py
jackbox/enums/player.py
jackbox/helpers/context.py
jackbox/objects/__init__.py
jackbox/objects/bombintern.py
jackbox/objects/player.py
jackbox/objects/blobs/__init__.py
jackbox/objects/blobs/bombintern.py
jackbox.py-0.1.0.dist-info/LICENSE
jackbox.py-0.1.0.dist-info/METADATA
jackbox.py-0.1.0.dist-info/WHEEL
jackbox.py-0.1.0.dist-info/top_level.txt
jackbox.py-0.1.0.dist-info/RECORD
