Metadata-Version: 2.1
Name: jackbox.py
Version: 0.1.0
Summary: An asynchronous Python framework for interacting with Jackbox Games.
Home-page: https://github.com/ShineyDev/jackbox.py
Author: ShineyDev
License: Apache Software License
Project-URL: Documentation, https://jackboxpy.readthedocs.io/en/latest/
Project-URL: Issue Tracker, https://github.com/ShineyDev/jackbox.py/issues/
Project-URL: Source, https://github.com/ShineyDev/jackbox.py/
Platform: UNKNOWN
Classifier: Development Status :: 5 - Production/Stable
Classifier: Intended Audience :: Developers
Classifier: License :: OSI Approved :: Apache Software License
Classifier: Natural Language :: English
Classifier: Operating System :: OS Independent
Classifier: Programming Language :: Python
Classifier: Programming Language :: Python :: 3 :: Only
Classifier: Programming Language :: Python :: 3.5
Classifier: Programming Language :: Python :: 3.6
Classifier: Programming Language :: Python :: 3.7
Classifier: Programming Language :: Python :: 3.8
Classifier: Programming Language :: Python :: Implementation :: CPython
Classifier: Topic :: Software Development
Classifier: Topic :: Software Development :: Libraries
Classifier: Topic :: Software Development :: Libraries :: Application Frameworks
Classifier: Topic :: Software Development :: Libraries :: Python Modules
Classifier: Topic :: Utilities
Classifier: Typing :: Typed
Requires-Python: >=3.5.2
Requires-Dist: aiohttp
Requires-Dist: websockets
Provides-Extra: docs
Requires-Dist: sphinx ; extra == 'docs'
Requires-Dist: sphinxcontrib-trio ; extra == 'docs'
